{
  "name": "madrid101-astro",
  "image": "mcr.microsoft.com/devcontainers/typescript-node:22",
  "features": {},
  "customizations": {
    "vscode": {
      "settings": {
        "json.schemas": [
          {
            "fileMatch": [
              "*/devcontainer-feature.json"
            ],
            "url": "https://raw.githubusercontent.com/devcontainers/spec/main/schemas/devContainerFeature.schema.json"
          }
        ]
      },
      "extensions": [
        "astro-build.astro-vscode",
        "biomejs.biome",
        "EditorConfig.EditorConfig"
      ]
    }
  }
}
